wikipediarevs.py
wikipediarevs-0.1.0.dist-info/METADATA
wikipediarevs-0.1.0.dist-info/WHEEL
wikipediarevs-0.1.0.dist-info/entry_points.txt
wikipediarevs-0.1.0.dist-info/top_level.txt
wikipediarevs-0.1.0.dist-info/zip-safe
wikipediarevs-0.1.0.dist-info/RECORD
