Metadata-Version: 2.1
Name: wikipediarevs
Version: 0.1.0
Summary: Download all the revisions for a set of Wikipedia articles
Home-page: https://github.com/edsu/wikipediarevs
Author: Ed Summers
Author-email: ehs@pobox.com
License: MIT
Requires-Dist: requests
